redisweb/__init__.py
redisweb/constant.py
redisweb/main.py
redisweb/redisboard.py
redisweb/utils.py
redisweb/static/dist/03783c5172ee1ad128c576bf88fac168.eot
redisweb/static/dist/073c2f3ce60eaf69cc2767ef3d989078.svg
redisweb/static/dist/8fdea4e89ac405d9f8db327adb331d8d.svg
redisweb/static/dist/acf50f59802f20d8b45220eaae532a1c.ttf
redisweb/static/dist/b557f56e367e59344ca95f9d1fb44352.svg
redisweb/static/dist/ed2b8bf117160466ba6220a8f1da54a4.ttf
redisweb/static/dist/ef3df98419d143d9617fe163bf4edc0b.eot
redisweb/static/dist/css/font.css
redisweb/static/dist/css/font.js
redisweb/static/dist/css/index.css
redisweb/static/dist/css/index.js
redisweb/static/dist/css/lib.css
redisweb/static/dist/css/lib.js
redisweb/static/dist/css/style.css
redisweb/static/dist/css/style.js
redisweb/static/dist/js/common.js
redisweb/static/dist/js/index.js
redisweb/static/dist/js/scripts.js
redisweb/static/dist/js/stisla.js
redisweb/static/dist/pages/command.js
redisweb/static/dist/pages/config.js
redisweb/static/dist/pages/dashboard.js
redisweb/static/dist/pages/database.js
redisweb/static/dist/pages/keydetail.js
redisweb/static/dist/pages/keydetail_hash.js
redisweb/static/dist/pages/keydetail_list.js
redisweb/static/dist/pages/keydetail_set.js
redisweb/static/dist/pages/keydetail_zset.js
redisweb/static/dist/pages/serverinfo.js
redisweb/templates/redisboard/command.html
redisweb/templates/redisboard/config.html
redisweb/templates/redisboard/dashboard.html
redisweb/templates/redisboard/database.html
redisweb/templates/redisboard/layout.html
redisweb/templates/redisboard/macros.html
redisweb/templates/redisboard/serverinfo.html
redisweb/templates/redisboard/keydetail/base.html
redisweb/templates/redisboard/keydetail/hash.html
redisweb/templates/redisboard/keydetail/list.html
redisweb/templates/redisboard/keydetail/set.html
redisweb/templates/redisboard/keydetail/string.html
redisweb/templates/redisboard/keydetail/zset.html
redisweb-1.0.8.dist-info/LICENSE
redisweb-1.0.8.dist-info/METADATA
redisweb-1.0.8.dist-info/WHEEL
redisweb-1.0.8.dist-info/entry_points.txt
redisweb-1.0.8.dist-info/top_level.txt
redisweb-1.0.8.dist-info/RECORD
